AUTHORS.rst
CONTRIBUTING.rst
HISTORY.rst
LICENSE
MANIFEST.in
README.rst
setup.cfg
setup.py
databuddy/__init__.py
databuddy/cli.py
databuddy/databuddy.py
databuddy/response_generators.py
databuddy/sqlalchemy_wrappers.py
databuddy.egg-info/PKG-INFO
databuddy.egg-info/SOURCES.txt
databuddy.egg-info/dependency_links.txt
databuddy.egg-info/entry_points.txt
databuddy.egg-info/not-zip-safe
databuddy.egg-info/requires.txt
databuddy.egg-info/top_level.txt
databuddy/databuddy_for_flask/__init__.py
databuddy/databuddy_for_flask/data_sources.py
databuddy/databuddy_for_flask/query_response_controller.py
databuddy/databuddy_for_flask/template_filters.py
databuddy/databuddy_for_flask/templates/databuddy/admin_theme/layout.html
databuddy/databuddy_for_flask/templates/databuddy/admin_theme/table_layout.html
databuddy/databuddy_for_flask/templates/databuddy/admin_theme/layout_sections/content_header.html
databuddy/databuddy_for_flask/templates/databuddy/admin_theme/layout_sections/foot_css.html
databuddy/databuddy_for_flask/templates/databuddy/admin_theme/layout_sections/foot_js.html
databuddy/databuddy_for_flask/templates/databuddy/admin_theme/layout_sections/head_css.html
databuddy/databuddy_for_flask/templates/databuddy/admin_theme/layout_sections/head_js.html
databuddy/databuddy_for_flask/templates/databuddy/admin_theme/layout_sections/left_navbar.html
databuddy/databuddy_for_flask/templates/databuddy/admin_theme/layout_sections/main_content.html
databuddy/databuddy_for_flask/templates/databuddy/admin_theme/layout_sections/topbar.html
databuddy/databuddy_for_flask/templates/databuddy/admin_theme/macros/layout_components.html
databuddy/databuddy_for_flask/templates/databuddy/default_theme/layout.html
databuddy/databuddy_for_flask/templates/databuddy/default_theme/table_layout.html
databuddy/databuddy_for_flask/templates/databuddy/default_theme/macros/layout_components.html
databuddy/databuddy_for_flask/templates/databuddy/default_theme/partials/content_header.html
databuddy/databuddy_for_flask/templates/databuddy/default_theme/partials/foot_js.html
databuddy/databuddy_for_flask/templates/databuddy/default_theme/partials/head_css.html
