Metadata-Version: 1.2
Name: databuddy
Version: 0.1.14
Summary: Tools to help create a data dashboard
Home-page: https://github.com/suryasankar/databuddy
Author: Surya Sankar
Author-email: suryashankar.m@gmail.com
License: MIT license
Keywords: databuddy
Platform: UNKNOWN
Classifier: Development Status :: 2 - Pre-Alpha
Classifier: Intended Audience :: Developers
Classifier: License :: OSI Approved :: MIT License
Classifier: Natural Language :: English
Classifier: Programming Language :: Python :: 3
Classifier: Programming Language :: Python :: 3.5
Classifier: Programming Language :: Python :: 3.6
Classifier: Programming Language :: Python :: 3.7
Classifier: Programming Language :: Python :: 3.8
Requires-Python: >=3.5
